topomap/HierarchicalTopoMap.py
topomap/TopoMap.py
topomap/TopoTree.py
topomap/UnionFindComponents.py
topomap/__init__.py
topomap/dataset_utils.py
topomap/test_utils.py
topomap/utils.py
topomap/visualizations.py
topomap-0.0.3.dist-info/LICENSE
topomap-0.0.3.dist-info/METADATA
topomap-0.0.3.dist-info/WHEEL
topomap-0.0.3.dist-info/top_level.txt
topomap-0.0.3.dist-info/RECORD
