Metadata-Version: 2.1
Name: topomap
Version: 0.0.3
Summary: TopoMap++: A faster and more space efficient technique to compute projections with topological guarantees
Home-page: https://github.com/VIDA-NYU/TopoMap-pp
Author: Vitoria Guardieiro, Felipe Inagaki de Oliveira, Harish Doraiswamy, Luis Gustavo Nonato, Claudio Silva
Author-email: vitoriaguardieiro@gmail.com
Keywords: Topological data analysis,Computational topology,High-dimensional data,Projection
Classifier: License :: OSI Approved :: BSD License
Classifier: Programming Language :: Python :: 3
Classifier: Operating System :: OS Independent
License-File: LICENSE
Requires-Dist: matplotlib >=3.8.2
Requires-Dist: mlpack >=4.3.0.post1
Requires-Dist: networkx >=3.2.1
Requires-Dist: numpy >=1.25.0
Requires-Dist: pandas >=2.2.2
Requires-Dist: plotly >=5.18.0
Requires-Dist: scikit-learn >=1.4.1.post1
Requires-Dist: scipy >=1.13.1
Requires-Dist: diskannpy ==0.7.0
